{"metadata": {"dbt_schema_version": "https://schemas.getdbt.com/dbt/run-results/v6.json", "dbt_version": "1.12.0", "generated_at": "2026-07-17T04:55:35.580392Z", "invocation_id": "3f448649-1e00-4e70-b453-432682aa02f1", "invocation_started_at": "2026-07-17T04:55:26.561562Z", "env": {}}, "results": [{"status": "success", "timing": [{"name": "compile", "started_at": "2026-07-17T04:55:35.205972Z", "completed_at": "2026-07-17T04:55:35.208610Z"}, {"name": "execute", "started_at": "2026-07-17T04:55:35.209142Z", "completed_at": "2026-07-17T04:55:35.209159Z"}], "thread_id": "Thread-5 (worker)", "execution_time": 0.016846895217895508, "adapter_response": {}, "message": null, "failures": null, "unique_id": "model.softcart.stg_orders", "compiled": true, "compiled_code": "with source as (\n    select * from softcart_db.raw.orders\n)\nselect\n    order_id,\n    customer_id,\n    order_date,\n    payment_method,\n    payment_status,\n    shipment_status,\n    order_total\nfrom source\nqualify row_number() over (partition by order_id order by order_date desc) = 1", "relation_name": "softcart_db.staging.stg_orders", "batch_results": null, "overload_results": null}, {"status": "success", "timing": [{"name": "compile", "started_at": "2026-07-17T04:55:35.203987Z", "completed_at": "2026-07-17T04:55:35.211264Z"}, {"name": "execute", "started_at": "2026-07-17T04:55:35.212902Z", "completed_at": "2026-07-17T04:55:35.212914Z"}], "thread_id": "Thread-4 (worker)", "execution_time": 0.021211624145507812, "adapter_response": {}, "message": null, "failures": null, "unique_id": "model.softcart.stg_order_items", "compiled": true, "compiled_code": "with source as (\n    select * from softcart_db.raw.order_items\n)\n\nselect\n    order_item_id,\n    order_id,\n    product_id,\n    quantity,\n    unit_price,\n    line_total\nfrom source", "relation_name": "softcart_db.staging.stg_order_items", "batch_results": null, "overload_results": null}, {"status": "success", "timing": [{"name": "compile", "started_at": "2026-07-17T04:55:35.202113Z", "completed_at": "2026-07-17T04:55:35.212370Z"}, {"name": "execute", "started_at": "2026-07-17T04:55:35.216129Z", "completed_at": "2026-07-17T04:55:35.216137Z"}], "thread_id": "Thread-3 (worker)", "execution_time": 0.025521039962768555, "adapter_response": {}, "message": null, "failures": null, "unique_id": "model.softcart.stg_customers", "compiled": true, "compiled_code": "with source as (\n    select * from softcart_db.raw.customers\n)\n\nselect\n    customer_id,\n    first_name,\n    last_name,\n    email,\n    signup_date,\n    city,\n    country\nfrom source", "relation_name": "softcart_db.staging.stg_customers", "batch_results": null, "overload_results": null}, {"status": "success", "timing": [{"name": "compile", "started_at": "2026-07-17T04:55:35.193552Z", "completed_at": "2026-07-17T04:55:35.215597Z"}, {"name": "execute", "started_at": "2026-07-17T04:55:35.217629Z", "completed_at": "2026-07-17T04:55:35.217639Z"}], "thread_id": "Thread-2 (worker)", "execution_time": 0.028617382049560547, "adapter_response": {}, "message": null, "failures": null, "unique_id": "model.softcart.stg_clickstream_events", "compiled": true, "compiled_code": "select\n    raw_event:event_id::string           as event_id,\n    raw_event:session_id::string         as session_id,\n    raw_event:customer_id::int           as customer_id,\n    raw_event:event_type::string         as event_type,\n    raw_event:product_id::int            as product_id,\n    raw_event:event_timestamp::timestamp as event_timestamp\nfrom softcart_db.raw.clickstream_events", "relation_name": "softcart_db.staging.stg_clickstream_events", "batch_results": null, "overload_results": null}, {"status": "success", "timing": [{"name": "compile", "started_at": "2026-07-17T04:55:35.213789Z", "completed_at": "2026-07-17T04:55:35.219292Z"}, {"name": "execute", "started_at": "2026-07-17T04:55:35.221965Z", "completed_at": "2026-07-17T04:55:35.221976Z"}], "thread_id": "Thread-5 (worker)", "execution_time": 0.011625051498413086, "adapter_response": {}, "message": null, "failures": null, "unique_id": "model.softcart.stg_products", "compiled": true, "compiled_code": "with source as (\n    select * from softcart_db.raw.products\n)\n\nselect\n    product_id,\n    product_name,\n    category,\n    brand,\n    unit_price\nfrom source", "relation_name": "softcart_db.staging.stg_products", "batch_results": null, "overload_results": null}, {"status": "success", "timing": [{"name": "compile", "started_at": "2026-07-17T04:55:35.232696Z", "completed_at": "2026-07-17T04:55:35.259726Z"}, {"name": "execute", "started_at": "2026-07-17T04:55:35.260271Z", "completed_at": "2026-07-17T04:55:35.260279Z"}], "thread_id": "Thread-3 (worker)", "execution_time": 0.039136409759521484, "adapter_response": {}, "message": null, "failures": null, "unique_id": "test.softcart.accepted_values_stg_orders_shipment_status__delivered__shipped__processing__cancelled.705adb6f01", "compiled": true, "compiled_code": "\n    \n    \n\nwith all_values as (\n\n    select\n        shipment_status as value_field,\n        count(*) as n_records\n\n    from softcart_db.staging.stg_orders\n    group by shipment_status\n\n)\n\nselect *\nfrom all_values\nwhere value_field not in (\n    'delivered','shipped','processing','cancelled'\n)\n\n\n", "relation_name": null, "batch_results": null, "overload_results": null}, {"status": "success", "timing": [{"name": "compile", "started_at": "2026-07-17T04:55:35.240226Z", "completed_at": "2026-07-17T04:55:35.267450Z"}, {"name": "execute", "started_at": "2026-07-17T04:55:35.268037Z", "completed_at": "2026-07-17T04:55:35.268046Z"}], "thread_id": "Thread-2 (worker)", "execution_time": 0.04486083984375, "adapter_response": {}, "message": null, "failures": null, "unique_id": "test.softcart.not_null_stg_orders_customer_id.af79d5e4b5", "compiled": true, "compiled_code": "\n    \n    \n\n\n\nselect customer_id\nfrom softcart_db.staging.stg_orders\nwhere customer_id is null\n\n\n", "relation_name": null, "batch_results": null, "overload_results": null}, {"status": "success", "timing": [{"name": "compile", "started_at": "2026-07-17T04:55:35.252782Z", "completed_at": "2026-07-17T04:55:35.273840Z"}, {"name": "execute", "started_at": "2026-07-17T04:55:35.275737Z", "completed_at": "2026-07-17T04:55:35.275748Z"}], "thread_id": "Thread-5 (worker)", "execution_time": 0.03621029853820801, "adapter_response": {}, "message": null, "failures": null, "unique_id": "test.softcart.not_null_stg_orders_order_id.81cfe2fe64", "compiled": true, "compiled_code": "\n    \n    \n\n\n\nselect order_id\nfrom softcart_db.staging.stg_orders\nwhere order_id is null\n\n\n", "relation_name": null, "batch_results": null, "overload_results": null}, {"status": "success", "timing": [{"name": "compile", "started_at": "2026-07-17T04:55:35.224923Z", "completed_at": "2026-07-17T04:55:35.274517Z"}, {"name": "execute", "started_at": "2026-07-17T04:55:35.277036Z", "completed_at": "2026-07-17T04:55:35.277044Z"}], "thread_id": "Thread-4 (worker)", "execution_time": 0.05728507041931152, "adapter_response": {}, "message": null, "failures": null, "unique_id": "test.softcart.accepted_values_stg_orders_payment_status__paid__failed__refunded__pending.e5cc705d1d", "compiled": true, "compiled_code": "\n    \n    \n\nwith all_values as (\n\n    select\n        payment_status as value_field,\n        count(*) as n_records\n\n    from softcart_db.staging.stg_orders\n    group by payment_status\n\n)\n\nselect *\nfrom all_values\nwhere value_field not in (\n    'paid','failed','refunded','pending'\n)\n\n\n", "relation_name": null, "batch_results": null, "overload_results": null}, {"status": "success", "timing": [{"name": "compile", "started_at": "2026-07-17T04:55:35.262819Z", "completed_at": "2026-07-17T04:55:35.276527Z"}, {"name": "execute", "started_at": "2026-07-17T04:55:35.278909Z", "completed_at": "2026-07-17T04:55:35.278917Z"}], "thread_id": "Thread-3 (worker)", "execution_time": 0.017285823822021484, "adapter_response": {}, "message": null, "failures": null, "unique_id": "test.softcart.unique_stg_orders_order_id.e3b841c71a", "compiled": true, "compiled_code": "\n    \n    \n\nselect\n    order_id as unique_field,\n    count(*) as n_records\n\nfrom softcart_db.staging.stg_orders\nwhere order_id is not null\ngroup by order_id\nhaving count(*) > 1\n\n\n", "relation_name": null, "batch_results": null, "overload_results": null}, {"status": "success", "timing": [{"name": "compile", "started_at": "2026-07-17T04:55:35.280298Z", "completed_at": "2026-07-17T04:55:35.288860Z"}, {"name": "execute", "started_at": "2026-07-17T04:55:35.302618Z", "completed_at": "2026-07-17T04:55:35.302629Z"}], "thread_id": "Thread-2 (worker)", "execution_time": 0.02772665023803711, "adapter_response": {}, "message": null, "failures": null, "unique_id": "model.softcart.fct_orders", "compiled": true, "compiled_code": "\nselect\n    oi.order_item_id,\n    oi.order_id,\n    o.customer_id,\n    oi.product_id,\n    o.order_date,\n    o.payment_method,\n    o.payment_status,\n    o.shipment_status,\n    oi.quantity,\n    oi.unit_price,\n    oi.line_total,\n    o.order_total\nfrom softcart_db.staging.stg_order_items oi\nleft join softcart_db.staging.stg_orders o\n    on oi.order_id = o.order_id\n\nwhere o.order_date > (select max(order_date) from softcart_db.marts.fct_orders)\n", "relation_name": "softcart_db.marts.fct_orders", "batch_results": null, "overload_results": null}, {"status": "success", "timing": [{"name": "compile", "started_at": "2026-07-17T04:55:35.304972Z", "completed_at": "2026-07-17T04:55:35.312878Z"}, {"name": "execute", "started_at": "2026-07-17T04:55:35.314970Z", "completed_at": "2026-07-17T04:55:35.314978Z"}], "thread_id": "Thread-3 (worker)", "execution_time": 0.027344465255737305, "adapter_response": {}, "message": null, "failures": null, "unique_id": "test.softcart.not_null_stg_order_items_product_id.5154a8a6f6", "compiled": true, "compiled_code": "\n    \n    \n\n\n\nselect product_id\nfrom softcart_db.staging.stg_order_items\nwhere product_id is null\n\n\n", "relation_name": null, "batch_results": null, "overload_results": null}, {"status": "success", "timing": [{"name": "compile", "started_at": "2026-07-17T04:55:35.289401Z", "completed_at": "2026-07-17T04:55:35.313951Z"}, {"name": "execute", "started_at": "2026-07-17T04:55:35.316326Z", "completed_at": "2026-07-17T04:55:35.316334Z"}], "thread_id": "Thread-5 (worker)", "execution_time": 0.031126022338867188, "adapter_response": {}, "message": null, "failures": null, "unique_id": "test.softcart.not_null_stg_order_items_order_id.2063801f96", "compiled": true, "compiled_code": "\n    \n    \n\n\n\nselect order_id\nfrom softcart_db.staging.stg_order_items\nwhere order_id is null\n\n\n", "relation_name": null, "batch_results": null, "overload_results": null}, {"status": "success", "timing": [{"name": "compile", "started_at": "2026-07-17T04:55:35.297483Z", "completed_at": "2026-07-17T04:55:35.314477Z"}, {"name": "execute", "started_at": "2026-07-17T04:55:35.317128Z", "completed_at": "2026-07-17T04:55:35.317136Z"}], "thread_id": "Thread-4 (worker)", "execution_time": 0.03064274787902832, "adapter_response": {}, "message": null, "failures": null, "unique_id": "test.softcart.not_null_stg_order_items_order_item_id.26a7e2bc35", "compiled": true, "compiled_code": "\n    \n    \n\n\n\nselect order_item_id\nfrom softcart_db.staging.stg_order_items\nwhere order_item_id is null\n\n\n", "relation_name": null, "batch_results": null, "overload_results": null}, {"status": "success", "timing": [{"name": "compile", "started_at": "2026-07-17T04:55:35.318512Z", "completed_at": "2026-07-17T04:55:35.333525Z"}, {"name": "execute", "started_at": "2026-07-17T04:55:35.340136Z", "completed_at": "2026-07-17T04:55:35.340145Z"}], "thread_id": "Thread-2 (worker)", "execution_time": 0.026826143264770508, "adapter_response": {}, "message": null, "failures": null, "unique_id": "test.softcart.relationships_stg_order_items_order_id__order_id__ref_stg_orders_.dbe9930c54", "compiled": true, "compiled_code": "\n    \n    \n\nwith child as (\n    select order_id as from_field\n    from softcart_db.staging.stg_order_items\n    where order_id is not null\n),\n\nparent as (\n    select order_id as to_field\n    from softcart_db.staging.stg_orders\n)\n\nselect\n    from_field\n\nfrom child\nleft join parent\n    on child.from_field = parent.to_field\n\nwhere parent.to_field is null\n\n\n", "relation_name": null, "batch_results": null, "overload_results": null}, {"status": "success", "timing": [{"name": "compile", "started_at": "2026-07-17T04:55:35.334974Z", "completed_at": "2026-07-17T04:55:35.347529Z"}, {"name": "execute", "started_at": "2026-07-17T04:55:35.349365Z", "completed_at": "2026-07-17T04:55:35.349373Z"}], "thread_id": "Thread-3 (worker)", "execution_time": 0.01825690269470215, "adapter_response": {}, "message": null, "failures": null, "unique_id": "test.softcart.unique_stg_order_items_order_item_id.90e333a108", "compiled": true, "compiled_code": "\n    \n    \n\nselect\n    order_item_id as unique_field,\n    count(*) as n_records\n\nfrom softcart_db.staging.stg_order_items\nwhere order_item_id is not null\ngroup by order_item_id\nhaving count(*) > 1\n\n\n", "relation_name": null, "batch_results": null, "overload_results": null}, {"status": "success", "timing": [{"name": "compile", "started_at": "2026-07-17T04:55:35.342599Z", "completed_at": "2026-07-17T04:55:35.348228Z"}, {"name": "execute", "started_at": "2026-07-17T04:55:35.350222Z", "completed_at": "2026-07-17T04:55:35.350232Z"}], "thread_id": "Thread-5 (worker)", "execution_time": 0.018543243408203125, "adapter_response": {}, "message": null, "failures": null, "unique_id": "model.softcart.dim_customers", "compiled": true, "compiled_code": "select\n    customer_id,\n    first_name,\n    last_name,\n    email,\n    signup_date,\n    city,\n    country\nfrom softcart_db.staging.stg_customers", "relation_name": "softcart_db.marts.dim_customers", "batch_results": null, "overload_results": null}, {"status": "success", "timing": [{"name": "compile", "started_at": "2026-07-17T04:55:35.344271Z", "completed_at": "2026-07-17T04:55:35.351524Z"}, {"name": "execute", "started_at": "2026-07-17T04:55:35.358348Z", "completed_at": "2026-07-17T04:55:35.358357Z"}], "thread_id": "Thread-4 (worker)", "execution_time": 0.026018142700195312, "adapter_response": {}, "message": null, "failures": null, "unique_id": "snapshot.softcart.dim_customers_snapshot", "compiled": true, "compiled_code": "\n\n\n\nselect\n    customer_id,\n    first_name,\n    last_name,\n    email,\n    signup_date,\n    city,\n    country\nfrom softcart_db.staging.stg_customers\n", "relation_name": "softcart_db.snapshots.dim_customers_snapshot", "batch_results": null, "overload_results": null}, {"status": "success", "timing": [{"name": "compile", "started_at": "2026-07-17T04:55:35.353187Z", "completed_at": "2026-07-17T04:55:35.363739Z"}, {"name": "execute", "started_at": "2026-07-17T04:55:35.383692Z", "completed_at": "2026-07-17T04:55:35.383702Z"}], "thread_id": "Thread-2 (worker)", "execution_time": 0.035073280334472656, "adapter_response": {}, "message": null, "failures": null, "unique_id": "test.softcart.not_null_stg_customers_customer_id.e2cfb1f9aa", "compiled": true, "compiled_code": "\n    \n    \n\n\n\nselect customer_id\nfrom softcart_db.staging.stg_customers\nwhere customer_id is null\n\n\n", "relation_name": null, "batch_results": null, "overload_results": null}, {"status": "success", "timing": [{"name": "compile", "started_at": "2026-07-17T04:55:35.369956Z", "completed_at": "2026-07-17T04:55:35.393292Z"}, {"name": "execute", "started_at": "2026-07-17T04:55:35.394978Z", "completed_at": "2026-07-17T04:55:35.394989Z"}], "thread_id": "Thread-5 (worker)", "execution_time": 0.0337061882019043, "adapter_response": {}, "message": null, "failures": null, "unique_id": "test.softcart.relationships_stg_orders_customer_id__customer_id__ref_stg_customers_.430bf21500", "compiled": true, "compiled_code": "\n    \n    \n\nwith child as (\n    select customer_id as from_field\n    from softcart_db.staging.stg_orders\n    where customer_id is not null\n),\n\nparent as (\n    select customer_id as to_field\n    from softcart_db.staging.stg_customers\n)\n\nselect\n    from_field\n\nfrom child\nleft join parent\n    on child.from_field = parent.to_field\n\nwhere parent.to_field is null\n\n\n", "relation_name": null, "batch_results": null, "overload_results": null}, {"status": "success", "timing": [{"name": "compile", "started_at": "2026-07-17T04:55:35.364814Z", "completed_at": "2026-07-17T04:55:35.393807Z"}, {"name": "execute", "started_at": "2026-07-17T04:55:35.396324Z", "completed_at": "2026-07-17T04:55:35.396331Z"}], "thread_id": "Thread-3 (worker)", "execution_time": 0.035582542419433594, "adapter_response": {}, "message": null, "failures": null, "unique_id": "test.softcart.not_null_stg_customers_email.d7cf761533", "compiled": true, "compiled_code": "\n    \n    \n\n\n\nselect email\nfrom softcart_db.staging.stg_customers\nwhere email is null\n\n\n", "relation_name": null, "batch_results": null, "overload_results": null}, {"status": "success", "timing": [{"name": "compile", "started_at": "2026-07-17T04:55:35.385931Z", "completed_at": "2026-07-17T04:55:35.395801Z"}, {"name": "execute", "started_at": "2026-07-17T04:55:35.400364Z", "completed_at": "2026-07-17T04:55:35.400373Z"}], "thread_id": "Thread-4 (worker)", "execution_time": 0.03620600700378418, "adapter_response": {}, "message": null, "failures": null, "unique_id": "test.softcart.unique_stg_customers_customer_id.c7614daada", "compiled": true, "compiled_code": "\n    \n    \n\nselect\n    customer_id as unique_field,\n    count(*) as n_records\n\nfrom softcart_db.staging.stg_customers\nwhere customer_id is not null\ngroup by customer_id\nhaving count(*) > 1\n\n\n", "relation_name": null, "batch_results": null, "overload_results": null}, {"status": "success", "timing": [{"name": "compile", "started_at": "2026-07-17T04:55:35.397128Z", "completed_at": "2026-07-17T04:55:35.403165Z"}, {"name": "execute", "started_at": "2026-07-17T04:55:35.406032Z", "completed_at": "2026-07-17T04:55:35.406043Z"}], "thread_id": "Thread-2 (worker)", "execution_time": 0.013527393341064453, "adapter_response": {}, "message": null, "failures": null, "unique_id": "model.softcart.fct_clickstream_events", "compiled": true, "compiled_code": "\n\nselect\n    event_id,\n    session_id,\n    customer_id,\n    event_type,\n    product_id,\n    event_timestamp\nfrom softcart_db.staging.stg_clickstream_events\n\n\nwhere event_timestamp > (select max(event_timestamp) from softcart_db.marts.fct_clickstream_events)\n", "relation_name": "softcart_db.marts.fct_clickstream_events", "batch_results": null, "overload_results": null}, {"status": "success", "timing": [{"name": "compile", "started_at": "2026-07-17T04:55:35.407382Z", "completed_at": "2026-07-17T04:55:35.421136Z"}, {"name": "execute", "started_at": "2026-07-17T04:55:35.422368Z", "completed_at": "2026-07-17T04:55:35.422376Z"}], "thread_id": "Thread-5 (worker)", "execution_time": 0.02055525779724121, "adapter_response": {}, "message": null, "failures": null, "unique_id": "model.softcart.dim_products", "compiled": true, "compiled_code": "select\n    product_id,\n    product_name,\n    category,\n    brand,\n    unit_price\nfrom softcart_db.staging.stg_products", "relation_name": "softcart_db.marts.dim_products", "batch_results": null, "overload_results": null}, {"status": "success", "timing": [{"name": "compile", "started_at": "2026-07-17T04:55:35.410602Z", "completed_at": "2026-07-17T04:55:35.423173Z"}, {"name": "execute", "started_at": "2026-07-17T04:55:35.435887Z", "completed_at": "2026-07-17T04:55:35.435901Z"}], "thread_id": "Thread-3 (worker)", "execution_time": 0.03193187713623047, "adapter_response": {}, "message": null, "failures": null, "unique_id": "snapshot.softcart.dim_products_snapshot", "compiled": true, "compiled_code": "\n\n\n\nselect\n    product_id,\n    product_name,\n    category,\n    brand,\n    unit_price\nfrom softcart_db.staging.stg_products\n", "relation_name": "softcart_db.snapshots.dim_products_snapshot", "batch_results": null, "overload_results": null}, {"status": "success", "timing": [{"name": "compile", "started_at": "2026-07-17T04:55:35.413300Z", "completed_at": "2026-07-17T04:55:35.436776Z"}, {"name": "execute", "started_at": "2026-07-17T04:55:35.438081Z", "completed_at": "2026-07-17T04:55:35.438091Z"}], "thread_id": "Thread-4 (worker)", "execution_time": 0.03298044204711914, "adapter_response": {}, "message": null, "failures": null, "unique_id": "test.softcart.not_null_stg_products_product_id.6373b0acf3", "compiled": true, "compiled_code": "\n    \n    \n\n\n\nselect product_id\nfrom softcart_db.staging.stg_products\nwhere product_id is null\n\n\n", "relation_name": null, "batch_results": null, "overload_results": null}, {"status": "success", "timing": [{"name": "compile", "started_at": "2026-07-17T04:55:35.423687Z", "completed_at": "2026-07-17T04:55:35.438857Z"}, {"name": "execute", "started_at": "2026-07-17T04:55:35.439966Z", "completed_at": "2026-07-17T04:55:35.439977Z"}], "thread_id": "Thread-2 (worker)", "execution_time": 0.021677017211914062, "adapter_response": {}, "message": null, "failures": null, "unique_id": "test.softcart.relationships_stg_order_items_product_id__product_id__ref_stg_products_.886a82c26c", "compiled": true, "compiled_code": "\n    \n    \n\nwith child as (\n    select product_id as from_field\n    from softcart_db.staging.stg_order_items\n    where product_id is not null\n),\n\nparent as (\n    select product_id as to_field\n    from softcart_db.staging.stg_products\n)\n\nselect\n    from_field\n\nfrom child\nleft join parent\n    on child.from_field = parent.to_field\n\nwhere parent.to_field is null\n\n\n", "relation_name": null, "batch_results": null, "overload_results": null}, {"status": "success", "timing": [{"name": "compile", "started_at": "2026-07-17T04:55:35.440813Z", "completed_at": "2026-07-17T04:55:35.447667Z"}, {"name": "execute", "started_at": "2026-07-17T04:55:35.448181Z", "completed_at": "2026-07-17T04:55:35.448188Z"}], "thread_id": "Thread-5 (worker)", "execution_time": 0.010989189147949219, "adapter_response": {}, "message": null, "failures": null, "unique_id": "test.softcart.unique_stg_products_product_id.7d950a1467", "compiled": true, "compiled_code": "\n    \n    \n\nselect\n    product_id as unique_field,\n    count(*) as n_records\n\nfrom softcart_db.staging.stg_products\nwhere product_id is not null\ngroup by product_id\nhaving count(*) > 1\n\n\n", "relation_name": null, "batch_results": null, "overload_results": null}], "elapsed_time": 5.67815375328064, "args": {"profiles_dir": "/home/runner/.dbt", "project_dir": ".", "require_valid_schema_from_generate_schema_name": false, "use_catalogs_v2": false, "log_format": "default", "require_ref_searches_node_package_before_root": false, "log_format_file": "debug", "partial_parse": true, "show_all_deprecations": false, "require_nested_cumulative_type_params": true, "skip_nodes_if_on_run_start_fails": true, "cache_selected_only": false, "v2_parser": "dbt-core-experimental-parser parse", "print": true, "require_explicit_package_overrides_for_builtin_materializations": true, "require_sql_header_in_test_configs": false, "empty_catalog": false, "support_custom_ref_kwargs": false, "version_check": true, "favor_state": false, "require_batched_execution_for_custom_microbatch_strategy": true, "which": "generate", "source_freshness_run_project_hooks": true, "exclude": [], "warn_error_options": {"error": [], "warn": [], "silence": []}, "use_v2_parser": false, "require_unique_project_resource_names": false, "state_modified_compare_vars": false, "sqlparse": {"MAX_GROUPING_DEPTH": null, "MAX_GROUPING_TOKENS": null}, "upload_to_artifacts_ingest_api": false, "use_colors_file": true, "maximum_seed_size_mib": 1, "invocation_command": "dbt docs generate --project-dir . --profiles-dir /home/runner/.dbt", "validate_macro_args": true, "require_generic_test_arguments_property": true, "require_corrected_analysis_fqns": false, "strict_mode": false, "state_modified_compare_more_unrendered_values": true, "macro_debugging": false, "partial_parse_file_diff": true, "vars": {}, "write_json": true, "require_resource_names_without_spaces": true, "log_file_max_bytes": 10485760, "latest_version_pointer_enabled_by_default": false, "introspect": true, "send_anonymous_usage_stats": true, "quiet": false, "defer": false, "require_source_and_semantic_model_names_without_spaces": false, "log_level_file": "debug", "select": [], "enable_grouped_warn_error_parser_logs": false, "compile": true, "populate_cache": true, "log_level": "info", "static": false, "indirect_selection": "eager", "allow_jinja_file_extensions": false, "require_yaml_configuration_for_mf_time_spines": true, "require_all_warnings_handled_by_warn_error": true, "hints_enabled": true, "static_parser": true, "show_resource_report": false, "use_colors": true, "printer_width": 80, "log_path": "logs", "use_fast_test_edges": false}}